daachorse-0.1.11.dist-info/METADATA
daachorse-0.1.11.dist-info/WHEEL
daachorse-0.1.11.dist-info/licenses/LICENSE-APACHE
daachorse-0.1.11.dist-info/licenses/LICENSE-MIT
daachorse/__init__.py
daachorse/__init__.pyi
daachorse/py.typed
daachorse/daachorse.cp311-win32.pyd
daachorse-0.1.11.dist-info/RECORD
