Metadata-Version: 2.4
Name: daachorse
Version: 0.1.11
Classifier: License :: OSI Approved :: Apache Software License
Classifier: License :: OSI Approved :: MIT License
Classifier: Programming Language :: Rust
Classifier: Topic :: Software Development :: Libraries
Classifier: Topic :: Text Processing
License-File: LICENSE-APACHE
License-File: LICENSE-MIT
Summary: A fast implementation of the Aho-Corasick algorithm using the compact double-array data structure
Home-Page: https://github.com/daac-tools/python-daachorse
Author: Koichi Akabe <vbkaisetsu@gmail.com>
Author-email: Koichi Akabe <vbkaisetsu@gmail.com>
License: MIT OR Apache-2.0
Project-URL: Source Code, https://github.com/daac-tools/python-daachorse
